llama_index/packs/evaluator_benchmarker/__init__.py
llama_index/packs/evaluator_benchmarker/base.py
llama_index_packs_evaluator_benchmarker-0.4.1.dist-info/METADATA
llama_index_packs_evaluator_benchmarker-0.4.1.dist-info/WHEEL
llama_index_packs_evaluator_benchmarker-0.4.1.dist-info/licenses/LICENSE
llama_index_packs_evaluator_benchmarker-0.4.1.dist-info/RECORD
